ff_adaptive/__init__.py
ff_adaptive/ff_adaptive.py
ff_adaptive-0.1.0.dist-info/licenses/LICENSE
ff_adaptive-0.1.0.dist-info/METADATA
ff_adaptive-0.1.0.dist-info/WHEEL
ff_adaptive-0.1.0.dist-info/top_level.txt
ff_adaptive-0.1.0.dist-info/RECORD
