Metadata-Version: 2.4
Name: ff-adaptive
Version: 0.1.0
Summary: Adaptive Retrieval component for Efficient Retrieval
Author: Martijn Smits
License: MIT License
Project-URL: Repository, https://github.com/martijnsmits/ffar
Keywords: information retrieval,corpus graph,efficient retrieval,adaptive retrieval
Classifier: Programming Language :: Python :: 3
Classifier: License :: OSI Approved :: MIT License
Classifier: Operating System :: OS Independent
Requires-Python: >=3.8
License-File: LICENSE
Requires-Dist: python-terrier<1,>=0.10.0
Requires-Dist: pyterrier-adaptive<1,>=0.1.0
Requires-Dist: pandas<3,>=2.0.3
Dynamic: license-file
